<consumable name="ConsumableCelticMercs_E">
		<icon>UserInterface\Icons\Consumable\ConCelticMercenaries4_C_ua</icon>
		<rollovertextid>59702</rollovertextid>
		<displaynameid>59698</displaynameid>
		<stackable/>
		<stacksize>20</stacksize>
		<offertype>eOfferCivMatching</offertype>
		<itemlevel>10</itemlevel>
		<sellable>true</sellable>
		<tradeable>true</tradeable>
		<destroyable>true</destroyable>
		<sellcostoverride>
			<capitalresource quantity="25">cCapResCoin</capitalresource>
		</sellcostoverride>
		<rarity>cRarityEpic</rarity>
		<power>PowerSpawnCelticMercs_E</power>
		<civmatchingtype>eCivMatchingTypeAny</civmatchingtype>
	</consumable>