<Unit id="931" name="Con_Inf_LongSwordsman_C">
		<DBID>2528</DBID>
		<DisplayNameID>62546</DisplayNameID>
		<EditorNameID>62547</EditorNameID>
		<UnitLevel>1</UnitLevel>
		<Trait1>ConCommonInf</Trait1>
		<ObstructionRadiusX>0.4900</ObstructionRadiusX>
		<ObstructionRadiusZ>0.4900</ObstructionRadiusZ>
		<FormationCategory>Body</FormationCategory>
		<MaxVelocity>7.0000</MaxVelocity>
		<MaxRunVelocity>10.5000</MaxRunVelocity>
		<MovementType>land</MovementType>
		<TurnRate>30.0000</TurnRate>
		<AnimFile>CivCelt\Units\Infantry\Longswordsman\LongswordsmanL0.xml</AnimFile>
		<CorpseDecalTime>0.0000</CorpseDecalTime>
		<ImpactType>Flesh</ImpactType>
		<PhysicsInfo>dude</PhysicsInfo>
		<Icon>\UserInterface\Icons\Units\CLongswordsman64_ua</Icon>
		<PortraitIcon>\UserInterface\Icons\Units\AvatarCLongswordsman_ua</PortraitIcon>
		<RolloverTextID>62545</RolloverTextID>
		<ShortRolloverTextID>62544</ShortRolloverTextID>
		<InitialHitpoints>210.0000</InitialHitpoints>
		<MaxHitpoints>210.0000</MaxHitpoints>
		<LOS>20.0000</LOS>
		<UnitAIType>HandCombative</UnitAIType>
		<TrainPoints>0.0000</TrainPoints>
		<Bounty>1.0000</Bounty>
		<CarryCapacity resourcetype="Food">100.0000</CarryCapacity>
		<AllowedAge>1</AllowedAge>
		<VisualScale>1.0000</VisualScale>
		<SoundFile>Ce_Inf_LongSwordsman</SoundFile>
		<Decay delay="0.2500" duration="0.1500"/>
		<UnitType>LogicalTypeAnimalsAttack</UnitType>
		<UnitType>LogicalTypeFailQuest</UnitType>
		<UnitType>LogicalTypeHealed</UnitType>
		<UnitType>LogicalTypeValidSharpshoot</UnitType>
		<UnitType>LogicalTypeNeededForVictory</UnitType>
		<UnitType>LogicalTypeHandUnitsAutoAttack</UnitType>
		<UnitType>LogicalTypeLandMilitary</UnitType>
		<UnitType>LogicalTypeScout</UnitType>
		<UnitType>LogicalTypeValidSPCUnitsDeadCondition</UnitType>
		<UnitType>LogicalTypeGarrisonInShips</UnitType>
		<UnitType>LogicalTypeRangedUnitsAutoAttack</UnitType>
		<UnitType>LogicalTypeVillagersAttack</UnitType>
		<UnitType>LogicalTypeHandUnitsAttack</UnitType>
		<UnitType>LogicalTypeRangedUnitsAttack</UnitType>
		<UnitType>LogicalTypeLandPickerChoice</UnitType>
		<UnitType>LogicalTypeLandPickerTarget</UnitType>
		<UnitType>LogicalTypeExplorer</UnitType>
		<UnitType>LogicalTypeMinimapFilterMilitary</UnitType>
		<UnitType>Unit</UnitType>
		<UnitType>UnitClass</UnitType>
		<UnitType>Military</UnitType>
		<UnitType>AbstractInfantry</UnitType>
		<UnitType>CountsTowardMilitaryScore</UnitType>
		<UnitType>ConvertsHerds</UnitType>
		<UnitType>AbstractTransportable</UnitType>
		<UnitType>UnitTypeInfantryAntiInf1</UnitType>
		<UnitType>ConvertableInfantry</UnitType>
		<UnitType>UnitTypeCounter</UnitType>
		<UnitType>UnitUpgradeAge2</UnitType>
		<UnitType>UnitUpgradeLevel13</UnitType>
		<UnitType>EquipmentFilterMilitary</UnitType>
		<Armor type="Hand" value="0.3000"/>
		<Flag>CollidesWithProjectiles</Flag>
		<Flag>ObscuredByUnits</Flag>
		<Flag>VisibleUnderFogIfGaia</Flag>
		<Flag>ShowGarrisonButton</Flag>
		<Flag>DontRotateObstruction</Flag>
		<Flag>ApplyHandicapTraining</Flag>
		<Flag>Tracked</Flag>
		<Command row="0" page="10" column="0">Stance1</Command>
		<Command row="0" page="10" column="2">Stance3</Command>
		<Command row="0" page="10" column="1">Delete</Command>
		<Tactics>melee.tactics</Tactics>
		<ProtoAction>
			<Name>MeleeAttack</Name>
			<DamageBonus type="AbstractInfantry">2.500000</DamageBonus>
			<Damage>12.000000</Damage>
			<ROF>0.000000</ROF>
			<DamageType>Hand</DamageType>
			<ImpactEffect>effects\impacts\sword</ImpactEffect>
		</ProtoAction>
	</Unit>