<Unit id="209" name="QuestGiverMaster">
		<DBID>1651</DBID>
		<DisplayNameID>51229</DisplayNameID>
		<EditorNameID>51230</EditorNameID>
		<ObstructionRadiusX>0.9900</ObstructionRadiusX>
		<ObstructionRadiusZ>0.9900</ObstructionRadiusZ>
		<FormationCategory>Ranged</FormationCategory>
		<MaxVelocity>6.0000</MaxVelocity>
		<MaxRunVelocity>9.0000</MaxRunVelocity>
		<MovementType>land</MovementType>
		<TurnRate>30.0000</TurnRate>
		<AnimFile>CivGreek\Units\QuestGivers\StoneQuestGiver\StoneQuestGiver.xml</AnimFile>
		<ImpactType>Flesh</ImpactType>
		<PhysicsInfo>dude</PhysicsInfo>
		<Icon>UserInterface\Icons\Units\QuestGiver64_ua</Icon>
		<PortraitIcon>UserInterface\Icons\Units\QuestGiver64_ua</PortraitIcon>
		<RolloverTextID>51228</RolloverTextID>
		<ShortRolloverTextID>51227</ShortRolloverTextID>
		<InitialHitpoints>2000.0000</InitialHitpoints>
		<MaxHitpoints>2000.0000</MaxHitpoints>
		<LOS>2.0000</LOS>
		<UnitAIType>HandCombative</UnitAIType>
		<TrainPoints>18.0000</TrainPoints>
		<AllowedAge>0</AllowedAge>
		<VisualScale>1.5000</VisualScale>
		<SoundFile>QuestGiverMaster</SoundFile>
		<UnitType>LogicalTypeAnimalsAttack</UnitType>
		<UnitType>LogicalTypeHealed</UnitType>
		<UnitType>LogicalTypeHandUnitsAutoAttack</UnitType>
		<UnitType>LogicalTypeGarrisonInShips</UnitType>
		<UnitType>LogicalTypeRangedUnitsAutoAttack</UnitType>
		<UnitType>LogicalTypeVillagersAttack</UnitType>
		<UnitType>LogicalTypeHandUnitsAttack</UnitType>
		<UnitType>LogicalTypeRangedUnitsAttack</UnitType>
		<UnitType>Unit</UnitType>
		<UnitType>UnitClass</UnitType>
		<Armor type="Hand" value="0.2500"/>
		<Flag>ObscuredByUnits</Flag>
		<Flag>Immoveable</Flag>
		<Flag>NotDeleteable</Flag>
		<Flag>VisibleUnderFogIfGaia</Flag>
		<Flag>NotCommandable</Flag>
		<Flag>DontRotateObstruction</Flag>
		<Flag>DecalStickToWaterSurface</Flag>
		<Flag>QuestGiver</Flag>
		<Flag>Tracked</Flag>
	</Unit>