<Unit id="742" name="Sheep">
		<DBID>2320</DBID>
		<DisplayNameID>60151</DisplayNameID>
		<EditorNameID>60152</EditorNameID>
		<ObstructionRadiusX>0.4900</ObstructionRadiusX>
		<ObstructionRadiusZ>0.4900</ObstructionRadiusZ>
		<FormationCategory>Protected</FormationCategory>
		<MaxVelocity>4.0000</MaxVelocity>
		<MaxRunVelocity>6.0000</MaxRunVelocity>
		<MovementType>land</MovementType>
		<TurnRate>10.0000</TurnRate>
		<WanderDistance>4</WanderDistance>
		<AnimFile>World\Resources\Sheep\Sheep.xml</AnimFile>
		<ImpactType>Flesh</ImpactType>
		<PhysicsInfo>dude</PhysicsInfo>
		<Icon>\UserInterface\Icons\Units\Gaia\Sheep64_ua</Icon>
		<PortraitIcon>\UserInterface\Icons\Units\Gaia\AvatarSheep_ua</PortraitIcon>
		<SelectionPriority>10</SelectionPriority>
		<RolloverTextID>60150</RolloverTextID>
		<ShortRolloverTextID>60149</ShortRolloverTextID>
		<InitialHitpoints>10.0000</InitialHitpoints>
		<MaxHitpoints>10.0000</MaxHitpoints>
		<LOS>8.0000</LOS>
		<UnitAIType>HerdAnimal</UnitAIType>
		<InitialResource resourcetype="Food">100.0000</InitialResource>
		<ResourceSubType>meat</ResourceSubType>
		<SoundFile>Goat</SoundFile>
		<GathererLimit>8</GathererLimit>
		<UnitType>LogicalTypeMinimapFilterEconomic</UnitType>
		<UnitType>LogicalTypeHealed</UnitType>
		<UnitType>LogicalTypeGarrisonInShips</UnitType>
		<UnitType>LogicalTypeVillagersAttack</UnitType>
		<UnitType>Unit</UnitType>
		<UnitType>Resource</UnitType>
		<UnitType>HuntedResource</UnitType>
		<UnitType>Food</UnitType>
		<UnitType>NatureClass</UnitType>
		<UnitType>Herdable</UnitType>
		<UnitType>StandardConvertable</UnitType>
		<UnitType>AbstractTransportable</UnitType>
		<Flag>CollidesWithProjectiles</Flag>
		<Flag>ObscuredByUnits</Flag>
		<Flag>DieAtZeroResources</Flag>
		<Flag>DoNotValidateResourceInventory</Flag>
		<Flag>DoNotDieAtZeroHitpoints</Flag>
		<Flag>NotDeleteable</Flag>
		<Flag>Doppled</Flag>
		<Flag>OrientUnitWithGround</Flag>
		<Flag>ConstrainOrientation</Flag>
		<Flag>ShowGarrisonButton</Flag>
		<Flag>DeadReplacementWhenDestroyed</Flag>
		<Flag>DontRotateObstruction</Flag>
		<Flag>RMCanRotate</Flag>
		<Flag>Tracked</Flag>
		<Tactics>questConvert.tactics</Tactics>
	</Unit>