<equipment version="0" id="331">
		<civ>Celtic</civ>
		<maxrank>1</maxrank>
		<icon>UserInterface\Icons\units\cwoadraider64_ua</icon>
		<largeicon>true</largeicon>
		<bldorunit>true</bldorunit>
		<questreward>false</questreward>
		<suppresseffects>true</suppresseffects>
		<displaynameid>700533</displaynameid>
		<uipanel>2</uipanel>
		<uirow>2</uirow>
		<uicol>0</uicol>
		<agerequirement>3</agerequirement>
		<grantedatlevel>false</grantedatlevel>
		<grantinglevel>0</grantinglevel>
		<ranks>
			<rank tech="Ce_Ct_UnitWoadRaider1" cost="2" descid="700638"/>
		</ranks>
		<prereq>332</prereq>
	</equipment>