<equipment version="0" id="39">
		<civ>Greek</civ>
		<maxrank>1</maxrank>
		<icon>UserInterface\Icons\units\ballista64_ua</icon>
		<largeicon>true</largeicon>
		<bldorunit>true</bldorunit>
		<questreward>false</questreward>
		<suppresseffects>true</suppresseffects>
		<displaynameid>700130</displaynameid>
		<uipanel>2</uipanel>
		<uirow>3</uirow>
		<uicol>49</uicol>
		<agerequirement>4</agerequirement>
		<offertype>eOfferNone</offertype>
		<grantedatlevel>false</grantedatlevel>
		<grantinglevel>0</grantinglevel>
		<ranks>
			<rank tech="GrE_GreekUnitBalista1" cost="3" descid="700131"/>
		</ranks>
		<prereq>35</prereq>
	</equipment>