<equipment version="0" id="391">
		<civ>Celtic</civ>
		<maxrank>1</maxrank>
		<icon>UserInterface\Icons\techs\greektechspearmans_ua</icon>
		<largeicon>false</largeicon>
		<bldorunit>false</bldorunit>
		<questreward>false</questreward>
		<suppresseffects>true</suppresseffects>
		<displaynameid>700193</displaynameid>
		<uipanel>2</uipanel>
		<uirow>7</uirow>
		<uicol>4</uicol>
		<agerequirement>4</agerequirement>
		<grantedatlevel>false</grantedatlevel>
		<grantinglevel>0</grantinglevel>
		<ranks>
			<rank tech="CeltTechSpearmanS" cost="2" descid="700505"/>
		</ranks>
		<prereq>390</prereq>
	</equipment>