<blueprint name="CeCraftStore04">
		<icon>UserInterface/Icons/Blueprints/BlueprintStore2_ua</icon>
		<rollovertextid>801113</rollovertextid>
		<displaynameid>801112</displaynameid>
		<stacksize>0</stacksize>
		<offertype>eOfferNone</offertype>
		<itemlevel>0</itemlevel>
		<sellable>true</sellable>
		<tradeable>true</tradeable>
		<destroyable>true</destroyable>
		<sellcostoverride>
			<capitalresource quantity="125">cCapResCoin</capitalresource>
		</sellcostoverride>
		<rarity>cRarityUncommon</rarity>
		<cost/>
		<protounit>Ce_Cap_BasicCraftStore04</protounit>
	</blueprint>